mcpsh/__init__.py
mcpsh/client.py
mcpsh/config.py
mcpsh/main.py
mcpsh-1.1.1.dist-info/WHEEL
mcpsh-1.1.1.dist-info/entry_points.txt
mcpsh-1.1.1.dist-info/METADATA
mcpsh-1.1.1.dist-info/RECORD
