Metadata-Version: 2.3
Name: mcpsh
Version: 1.1.1
Summary: Progressive CLI and Python API for MCP servers - discover tools naturally and import directly in scripts
Keywords: mcp,model-context-protocol,cli,fastmcp,tools
Author: Foad Kesheh
License: MIT
Classifier: Development Status :: 4 - Beta
Classifier: Intended Audience :: Developers
Classifier: License :: OSI Approved :: MIT License
Classifier: Programming Language :: Python :: 3
Classifier: Programming Language :: Python :: 3.10
Classifier: Programming Language :: Python :: 3.11
Classifier: Programming Language :: Python :: 3.12
Classifier: Programming Language :: Python :: 3.13
Classifier: Topic :: Software Development :: Libraries :: Python Modules
Classifier: Topic :: System :: Shells
Requires-Dist: fastmcp>=2.12.5,<3.0.0
Requires-Dist: rich>=14.2.0
Requires-Dist: typer>=0.20.0
Requires-Dist: pytest>=9.0.0 ; extra == 'dev'
Requires-Dist: pytest-asyncio>=0.23.0 ; extra == 'dev'
Requires-Dist: pytest-cov>=4.1.0 ; extra == 'dev'
Requires-Dist: pytest-timeout>=2.2.0 ; extra == 'dev'
Requires-Dist: psutil>=7.1.3 ; extra == 'dev'
Requires-Python: >=3.10, <4.0
Project-URL: Homepage, https://github.com/fkesheh/mcpsh
Project-URL: Issues, https://github.com/fkesheh/mcpsh/issues
Project-URL: Repository, https://github.com/fkesheh/mcpsh
Provides-Extra: dev
